code_sync/__init__.py
code_sync/code_sync.py
code_sync-0.3.0.dist-info/LICENSE
code_sync-0.3.0.dist-info/METADATA
code_sync-0.3.0.dist-info/WHEEL
code_sync-0.3.0.dist-info/entry_points.txt
code_sync-0.3.0.dist-info/top_level.txt
code_sync-0.3.0.dist-info/RECORD
