Metadata-Version: 2.1
Name: code-sync
Version: 0.3.0
Summary: Sync code to a remote machine
Home-page: https://github.com/uzh-dqbm-cmi/code-sync
License: UNKNOWN
Project-URL: Bug Tracker, https://github.com/uzh-dqbm-cmi/code-sync/issues
Project-URL: Documentation, https://github.com/uzh-dqbm-cmi/code-sync
Project-URL: Source Code, https://github.com/uzh-dqbm-cmi/code-sync
Platform: UNKNOWN
Classifier: Programming Language :: Python :: 3
Classifier: License :: OSI Approved :: MIT License
Classifier: Operating System :: OS Independent
Classifier: Development Status :: 2 - Pre-Alpha
Classifier: Intended Audience :: Science/Research
Classifier: Topic :: Scientific/Engineering
Requires-Python: >3.6.0
Requires-Dist: watchdog
Requires-Dist: pyyaml
Requires-Dist: argh
